management_tools/__init__.py
management_tools/exceptions.py
management_tools/client/__init__.py
management_tools/client/base.py
management_tools/client/jira.py
management_tools/email/__init__.py
management_tools/email/base.py
management_tools/email/exchange.py
management_tools-0.4.0.dist-info/DESCRIPTION.rst
management_tools-0.4.0.dist-info/LICENSE.txt
management_tools-0.4.0.dist-info/METADATA
management_tools-0.4.0.dist-info/RECORD
management_tools-0.4.0.dist-info/WHEEL
management_tools-0.4.0.dist-info/metadata.json
management_tools-0.4.0.dist-info/top_level.txt
