Metadata-Version: 2.0
Name: management-tools
Version: 0.4.0
Summary: A set of tools to measure and improve efficiency in team management tasks.
Home-page: https://github.com/PeRDy/management-tools
Author: José Antonio Perdiguero López
Author-email: perdy.hh@gmail.com
License: GPLv3
Download-URL: https://github.com/PeRDy/management-tools
Keywords: python management tools jira rest client api
Platform: UNKNOWN
Classifier: Development Status :: 5 - Production/Stable
Classifier: Intended Audience :: Developers
Classifier: License :: OSI Approved :: GNU General Public License v3 (GPLv3)
Classifier: Natural Language :: English
Classifier: Programming Language :: Python
Classifier: Programming Language :: Python :: 3.5
Classifier: Programming Language :: Python :: 3.6
Classifier: Topic :: Software Development :: Libraries :: Python Modules
Requires-Dist: exchangelib
Requires-Dist: requests (>=2.8)
Provides-Extra: dev
Requires-Dist: bumpversion; extra == 'dev'
Requires-Dist: coverage; extra == 'dev'
Requires-Dist: exchangelib; extra == 'dev'
Requires-Dist: nose; extra == 'dev'
Requires-Dist: pip; extra == 'dev'
Requires-Dist: pre-commit; extra == 'dev'
Requires-Dist: prospector; extra == 'dev'
Requires-Dist: requests (>=2.8); extra == 'dev'
Requires-Dist: setuptools; extra == 'dev'
Requires-Dist: tox; extra == 'dev'
Requires-Dist: twine; extra == 'dev'
Requires-Dist: wheel; extra == 'dev'
